svg_translate/__init__.py
svg_translate/text_utils.py
svg_translate/workflows.py
svg_translate/extraction/__init__.py
svg_translate/extraction/extractor.py
svg_translate/injection/__init__.py
svg_translate/injection/batch.py
svg_translate/injection/injector.py
svg_translate/injection/preparation.py
svg_translate-0.1.0.dist-info/METADATA
svg_translate-0.1.0.dist-info/WHEEL
svg_translate-0.1.0.dist-info/RECORD
