Metadata-Version: 2.4
Name: svg-translate
Version: 0.1.0
Summary: Utilities for extracting and applying translations to multilingual SVG files.
Project-URL: Homepage, https://github.com/MrIbrahem/svg_translate_py
Project-URL: Repository, https://github.com/MrIbrahem/svg_translate_py
Project-URL: Issues, https://github.com/MrIbrahem/svg_translate_py/issues
Author: SVG Translate Team
License: MIT
Requires-Python: >=3.10
Requires-Dist: lxml>=4.9
